clearblade/ClearBladeCore.py
clearblade/Code.py
clearblade/Collections.py
clearblade/Developers.py
clearblade/Devices.py
clearblade/Messaging.py
clearblade/Permissions.py
clearblade/Users.py
clearblade/__init__.py
clearblade/cbErrors.py
clearblade/cbLogs.py
clearblade/restcall.py
clearblade-2.4.7.dist-info/LICENSE.txt
clearblade-2.4.7.dist-info/METADATA
clearblade-2.4.7.dist-info/WHEEL
clearblade-2.4.7.dist-info/top_level.txt
clearblade-2.4.7.dist-info/RECORD
