Metadata-Version: 2.1
Name: clearblade
Version: 2.4.7
Summary: A Python SDK for interacting with the ClearBlade Platform.
Home-page: https://github.com/ClearBlade/ClearBlade-Python-SDK
Download-URL: https://github.com/ClearBlade/ClearBlade-Python-SDK/archive/v2.4.7.tar.gz
Maintainer: Aaron Allsbrook
Maintainer-email: dev@clearblade.com
Keywords: clearblade,iot,sdk
License-File: LICENSE.txt
Requires-Dist: paho-mqtt >=1.3.0
Requires-Dist: requests
